minemind/__init__.py
minemind/client.py
minemind/dispatcher.py
minemind/main.py
minemind/mc_types/__init__.py
minemind/mc_types/array.py
minemind/mc_types/base.py
minemind/mc_types/boolean.py
minemind/mc_types/float.py
minemind/mc_types/int.py
minemind/mc_types/nbt.py
minemind/mc_types/position.py
minemind/mc_types/string.py
minemind/mc_types/uuid.py
minemind/mc_types/varnum.py
minemind/protocols/__init__.py
minemind/protocols/base.py
minemind/protocols/enums.py
minemind/protocols/protocol_events.py
minemind/protocols/utils.py
minemind/protocols/v765/__init__.py
minemind/protocols/v765/bot.py
minemind/protocols/v765/configuration.py
minemind/protocols/v765/constants.py
minemind/protocols/v765/entity.py
minemind/protocols/v765/game.py
minemind/protocols/v765/handshake.py
minemind/protocols/v765/inbound/__init__.py
minemind/protocols/v765/inbound/configuration.py
minemind/protocols/v765/inbound/login.py
minemind/protocols/v765/inbound/play.py
minemind/protocols/v765/inbound/status.py
minemind/protocols/v765/minecraft-data/biomes.json
minemind/protocols/v765/minecraft-data/blockCollisionShapes.json
minemind/protocols/v765/minecraft-data/blocks.json
minemind/protocols/v765/outbound/__init__.py
minemind/protocols/v765/outbound/configuration.py
minemind/protocols/v765/outbound/handshaking.py
minemind/protocols/v765/outbound/login.py
minemind/protocols/v765/outbound/play.py
minemind/protocols/v765/outbound/status.py
minemind/protocols/v765/physics.py
minemind/protocols/v765/server.py
minemind/protocols/v765/world.py
minemind-0.1.0.dist-info/METADATA
minemind-0.1.0.dist-info/WHEEL
minemind-0.1.0.dist-info/RECORD
