Metadata-Version: 2.1
Name: minemind
Version: 0.1.0
Summary: Low-level API for creating minecraft bots
Author: iYasha
Author-email: 33287747+iYasha@users.noreply.github.com
Requires-Python: >=3.11,<4.0
Classifier: Programming Language :: Python :: 3
Classifier: Programming Language :: Python :: 3.11
Classifier: Programming Language :: Python :: 3.12
Requires-Dist: pytz (>=2024.2,<2025.0)
Requires-Dist: requests (>=2.32.3,<3.0.0)
